alumathunique/__init__.py
alumathunique/matrix_multiply.py
alumathunique-0.1.0.dist-info/licenses/LICENSE.txt
tests/__init__.py
tests/test_matrix_multiply.py
alumathunique-0.1.0.dist-info/METADATA
alumathunique-0.1.0.dist-info/WHEEL
alumathunique-0.1.0.dist-info/top_level.txt
alumathunique-0.1.0.dist-info/RECORD
