Metadata-Version: 2.4
Name: alumathunique
Version: 0.1.0
Summary: Matrix multiplication with personality and humor!
Author: Belyse, Elyse, Bella
Classifier: Programming Language :: Python :: 3
Classifier: Operating System :: OS Independent
Requires-Python: >=3.7
License-File: LICENSE.txt
Dynamic: author
Dynamic: classifier
Dynamic: license-file
Dynamic: requires-python
Dynamic: summary
